odoo/addons/purchase_order_type_dashboard/README.rst
odoo/addons/purchase_order_type_dashboard/__init__.py
odoo/addons/purchase_order_type_dashboard/__manifest__.py
odoo/addons/purchase_order_type_dashboard/demo/purchase_order_type_dashboard.xml
odoo/addons/purchase_order_type_dashboard/i18n/es.po
odoo/addons/purchase_order_type_dashboard/i18n/it.po
odoo/addons/purchase_order_type_dashboard/i18n/pt_BR.po
odoo/addons/purchase_order_type_dashboard/i18n/purchase_order_type_dashboard.pot
odoo/addons/purchase_order_type_dashboard/models/__init__.py
odoo/addons/purchase_order_type_dashboard/models/purchase_order_type.py
odoo/addons/purchase_order_type_dashboard/readme/CONTRIBUTORS.md
odoo/addons/purchase_order_type_dashboard/readme/DESCRIPTION.md
odoo/addons/purchase_order_type_dashboard/static/description/icon.png
odoo/addons/purchase_order_type_dashboard/static/description/index.html
odoo/addons/purchase_order_type_dashboard/tests/__init__.py
odoo/addons/purchase_order_type_dashboard/tests/test_purchase_order_type_dashboard.py
odoo/addons/purchase_order_type_dashboard/views/menu_purchase_order.xml
odoo/addons/purchase_order_type_dashboard/views/view_purchase_order.xml
odoo/addons/purchase_order_type_dashboard/views/view_purchase_order_type.xml
odoo_addon_purchase_order_type_dashboard-18.0.1.0.0.4.dist-info/METADATA
odoo_addon_purchase_order_type_dashboard-18.0.1.0.0.4.dist-info/WHEEL
odoo_addon_purchase_order_type_dashboard-18.0.1.0.0.4.dist-info/top_level.txt
odoo_addon_purchase_order_type_dashboard-18.0.1.0.0.4.dist-info/RECORD
