Metadata-Version: 2.1
Name: odoo-addon-purchase_order_type_dashboard
Version: 18.0.1.0.0.4
Requires-Python: >=3.10
Requires-Dist: odoo-addon-purchase_order_type==18.0.*
Requires-Dist: odoo==18.0.*
Summary: Purchase Order Type Dashboard
Home-page: https://github.com/OCA/purchase-workflow
License: AGPL-3
Author: Solvos, Odoo Community Association (OCA)
Author-email: support@odoo-community.org
Classifier: Programming Language :: Python
Classifier: Framework :: Odoo
Classifier: Framework :: Odoo :: 18.0
Classifier: License :: OSI Approved :: GNU Affero General Public License v3
